fluentcms_suit/__init__.py
fluentcms_suit/admin.py
fluentcms_suit/apps.py
fluentcms_suit/models.py
fluentcms_suit/locale/ru/LC_MESSAGES/django.mo
fluentcms_suit/locale/ru/LC_MESSAGES/django.po
fluentcms_suit/static/fluent_contents/admin/cp_admin.css
fluentcms_suit/static/fluent_contents/admin/cp_admin_classic.css
fluentcms_suit/static/fluent_contents/admin/cp_admin_flat.css
fluentcms_suit/static/fluent_contents/code/code_admin.css
fluentcms_suit/static/fluent_contents/plugins/markup/markup_admin.css
fluentcms_suit/static/fluent_contents/plugins/oembed/oembed_admin.css
fluentcms_suit/static/fluent_contents/plugins/rawhtml/rawhtml_admin.css
fluentcms_suit/static/parler/admin/parler_admin.css
fluentcms_suit/static/parler/admin/parler_admin_flat.css
fluentcms_suit/static/polymorphic_tree/adminlist/nodetree.css
fluentcms_suit/static/polymorphic_tree/adminlist/nodetree_classic.css
fluentcms_suit/static/slug_preview/css/slug_preview.css
fluentcms_suit/static/suit/js/jquery-1.12.4.min.js
fluentcms_suit/templates/admin/mptt_change_list.html
fluentcms_suit/templates/admin/fluent_contents/fieldset.html
fluentcms_suit/templates/admin/fluent_contents/fieldset_line.html
fluentcms_suit/templates/admin/fluent_contents/fieldset_line_without_labels.html
fluentcms_suit/templates/admin/fluent_contents/fieldset_without_labels.html
fluentcms_suit/templates/admin/fluent_contents/contentitem/inline_container.html
fluentcms_suit/templates/admin/fluent_contents/placeholder/inline_tabs.html
fluentcms_suit/templates/admin/fluent_contents/placeholderfield/controls.html
fluentcms_suit/templates/admin/fluent_contents/plugins/code/admin_form.html
fluentcms_suit/templates/admin/fluent_contents/plugins/oembeditem/admin_form.html
fluentcms_suit/templates/admin/fluent_contents/plugins/oembeditem/fieldset.html
fluentcms_suit/templates/admin/fluent_pages/page/base_change_form.html
fluentcms_suit/templates/admin/fluent_pages/page/delete_confirmation.html
fluentcms_suit-2.0.1.dist-info/AUTHORS
fluentcms_suit-2.0.1.dist-info/LICENSE
fluentcms_suit-2.0.1.dist-info/METADATA
fluentcms_suit-2.0.1.dist-info/WHEEL
fluentcms_suit-2.0.1.dist-info/top_level.txt
fluentcms_suit-2.0.1.dist-info/RECORD
